efb_link_preview_middleware/__init__.py
efb_link_preview_middleware/__version__.py
efb_link_preview_middleware-0.1.0.dist-info/METADATA
efb_link_preview_middleware-0.1.0.dist-info/WHEEL
efb_link_preview_middleware-0.1.0.dist-info/entry_points.txt
efb_link_preview_middleware-0.1.0.dist-info/top_level.txt
efb_link_preview_middleware-0.1.0.dist-info/RECORD
