Metadata-Version: 2.1
Name: efb-link-preview-middleware
Version: 0.1.0
Summary: WeChat Middleware of EH Forwarder Bot for link preview
Home-page: UNKNOWN
Author: catbaron
Author-email: catbaron@live.cn
License: AGPLv3+
Keywords: ehforwarderbot,EH Forwarder Bot,EH Forwarder Bot Middleware,chatbot,link preview
Platform: UNKNOWN
Classifier: Development Status :: 5 - Production/Stable
Classifier: License :: OSI Approved :: GNU Affero General Public License v3 or later (AGPLv3+)
Classifier: Intended Audience :: Developers
Classifier: Intended Audience :: End Users/Desktop
Classifier: Programming Language :: Python :: 3 :: Only
Classifier: Programming Language :: Python :: 3.6
Classifier: Programming Language :: Python :: 3.6
Classifier: Topic :: Communications :: Chat
Classifier: Topic :: Utilities
Requires-Python: >=3.6
Requires-Dist: ehforwarderbot (>=2.0.0b15)
Requires-Dist: python-telegram-bot (>=10.0.0<12.0.0)
Requires-Dist: beautifulsoup4
